chatgpt_utils/__init__.py
chatgpt_utils/classification.py
chatgpt_utils/embeddings.py
chatgpt_utils/embeddings/__init__.py
chatgpt_utils/embeddings/embeddings.py
chatgpt_utils/embeddings/utils.py
chatgpt_utils/parse/__init__.py
chatgpt_utils/parse/delimiter_parser.py
chatgpt_utils/parse/json_parser.py
chatgpt_utils/prompt/PromptDesigner.py
chatgpt_utils/prompt/__init__.py
chatgpt_utils/prompt/utils.py
openai_utils/DataUnit.py
openai_utils/__init__.py
openai_utils/utils.py
openai_utils/chatcompletion/__init__.py
openai_utils/chatcompletion/azure_openai_chatgpt.py
openai_utils/chatcompletion/base.py
openai_utils/chatcompletion/chatgpt.py
openai_utils/chatcompletion/openai_chatgpt.py
openai_utils/config/__init__.py
openai_utils/config/huggingface_config.py
openai_utils/config/openai_config.py
openai_utils/embeddings/__init__.py
openai_utils/embeddings/base.py
openai_utils/embeddings/embeddings.py
openai_utils/embeddings/huggingface_embeddings.py
openai_utils/embeddings/openai_embeddings.py
openai_utils/embeddings/utils.py
openai_utils/parse/__init__.py
openai_utils/parse/delimiter_parser.py
openai_utils/parse/json_parser.py
openai_utils/prompt/PromptDesigner.py
openai_utils/prompt/__init__.py
ching_chatgpt_utils-0.1.5.dist-info/LICENSE
ching_chatgpt_utils-0.1.5.dist-info/METADATA
ching_chatgpt_utils-0.1.5.dist-info/WHEEL
ching_chatgpt_utils-0.1.5.dist-info/top_level.txt
ching_chatgpt_utils-0.1.5.dist-info/RECORD
