Metadata-Version: 2.1
Name: ching-chatgpt-utils
Version: 0.1.5
Summary: This package has some useful functions for ChatGPT workflows - Writing Prompts
Home-page: https://github.com/pypa/sampleproject
Author: Ching Fhen
Author-email: dsai.chingfhen@gmail.com
Project-URL: Bug Tracker, https://github.com/pypa/sampleproject/issues
Classifier: Programming Language :: Python :: 3
Classifier: License :: OSI Approved :: MIT License
Classifier: Operating System :: OS Independent
Requires-Python: >=3.6
License-File: LICENSE
Requires-Dist: regex
Requires-Dist: openai
Requires-Dist: PyYAML
Requires-Dist: pydantic
